{
  "directed": false,
  "multigraph": false,
  "graph": {
    "hyperedges": [
      {
        "id": "hg_persist_interface_contracts",
        "label": "Casbin persist interface contracts the Adapter implements",
        "nodes": [
          "2026_05_07_gorm_adapter_baseline_design_ac_001_persist_adapter",
          "2026_05_07_gorm_adapter_baseline_design_ac_002_persist_filteredadapter",
          "2026_05_07_gorm_adapter_baseline_design_ac_003_persist_batchadapter",
          "2026_05_07_gorm_adapter_baseline_design_ac_004_persist_updatableadapter",
          "adapter_adapter"
        ],
        "relation": "implement",
        "confidence": "EXTRACTED",
        "confidence_score": 1.0,
        "source_file": "docs/superpowers/specs/2026-05-07-gorm-adapter-baseline-design.md"
      },
      {
        "id": "hg_six_constructors_minimal_surface",
        "label": "Six top-level constructors governed by Minimal Surface principle",
        "nodes": [
          "adapter_newadapter",
          "adapter_newadapterbydb",
          "adapter_newadapterbydbusetablename",
          "adapter_newadapterbydbwithcustomtable",
          "adapter_newfilteredadapter",
          "adapter_newadapterbymuldb",
          "2026_05_07_gorm_adapter_baseline_design_ac_008_six_constructors"
        ],
        "relation": "participate_in",
        "confidence": "EXTRACTED",
        "confidence_score": 1.0,
        "source_file": "docs/superpowers/specs/2026-05-07-gorm-adapter-baseline-design.md"
      },
      {
        "id": "hg_three_priority_usage_scenarios",
        "label": "Three Usage Scenarios (P1/P2/P3) framing baseline behaviour",
        "nodes": [
          "2026_05_07_gorm_adapter_baseline_design_usage_scenario_1_persist_policy",
          "2026_05_07_gorm_adapter_baseline_design_usage_scenario_2_existing_gorm_db",
          "2026_05_07_gorm_adapter_baseline_design_usage_scenario_3_filtered_policy_loading",
          "2026_05_07_gorm_adapter_baseline_design_baseline_spec"
        ],
        "relation": "form",
        "confidence": "EXTRACTED",
        "confidence_score": 1.0,
        "source_file": "docs/superpowers/specs/2026-05-07-gorm-adapter-baseline-design.md"
      }
    ]
  },
  "nodes": [
    {
      "label": "CasbinRule struct",
      "file_type": "code",
      "source_file": "adapter.go",
      "source_location": "adapter.go:26-37",
      "source_url": null,
      "captured_at": null,
      "author": null,
      "contributor": null,
      "id": "adapter_casbinrule",
      "community": 7,
      "norm_label": "casbinrule struct"
    },
    {
      "label": "Filter struct",
      "file_type": "code",
      "source_file": "adapter.go",
      "source_location": "adapter.go:43-53",
      "source_url": null,
      "captured_at": null,
      "author": null,
      "contributor": null,
      "id": "adapter_filter",
      "community": 0,
      "norm_label": "filter struct"
    },
    {
      "label": "Adapter struct",
      "file_type": "code",
      "source_file": "adapter.go",
      "source_location": "adapter.go:56-65",
      "source_url": null,
      "captured_at": null,
      "author": null,
      "contributor": null,
      "id": "adapter_adapter",
      "community": 8,
      "norm_label": "adapter struct"
    },
    {
      "label": "finalizer",
      "file_type": "code",
      "source_file": "adapter.go",
      "source_location": "adapter.go:68-77",
      "source_url": null,
      "captured_at": null,
      "author": null,
      "contributor": null,
      "id": "adapter_finalizer",
      "community": 8,
      "norm_label": "finalizer"
    },
    {
      "label": "specificPolicy type",
      "file_type": "code",
      "source_file": "adapter.go",
      "source_location": "adapter.go:80-84",
      "source_url": null,
      "captured_at": null,
      "author": null,
      "contributor": null,
      "id": "adapter_specificpolicy",
      "community": 2,
      "norm_label": "specificpolicy type"
    },
    {
      "label": "DbPool struct",
      "file_type": "code",
      "source_file": "adapter.go",
      "source_location": "adapter.go:86-90",
      "source_url": null,
      "captured_at": null,
      "author": null,
      "contributor": null,
      "id": "adapter_dbpool",
      "community": 2,
      "norm_label": "dbpool struct"
    },
    {
      "label": "DbPool.switchDb",
      "file_type": "code",
      "source_file": "adapter.go",
      "source_location": "adapter.go:92-95",
      "source_url": null,
      "captured_at": null,
      "author": null,
      "contributor": null,
      "id": "adapter_dbpool_switchdb",
      "community": 2,
      "norm_label": "dbpool.switchdb"
    },
    {
      "label": "NewAdapter constructor",
      "file_type": "code",
      "source_file": "adapter.go",
      "source_location": "adapter.go:108-167",
      "source_url": null,
      "captured_at": null,
      "author": null,
      "contributor": null,
      "id": "adapter_newadapter",
      "community": 4,
      "norm_label": "newadapter constructor"
    },
    {
      "label": "NewAdapterByDBUseTableName",
      "file_type": "code",
      "source_file": "adapter.go",
      "source_location": "adapter.go:171-189",
      "source_url": null,
      "captured_at": null,
      "author": null,
      "contributor": null,
      "id": "adapter_newadapterbydbusetablename",
      "community": 3,
      "norm_label": "newadapterbydbusetablename"
    },
    {
      "label": "InitDbResolver",
      "file_type": "code",
      "source_file": "adapter.go",
      "source_location": "adapter.go:196-212",
      "source_url": null,
      "captured_at": null,
      "author": null,
      "contributor": null,
      "id": "adapter_initdbresolver",
      "community": 2,
      "norm_label": "initdbresolver"
    },
    {
      "label": "NewAdapterByMulDb",
      "file_type": "code",
      "source_file": "adapter.go",
      "source_location": "adapter.go:214-219",
      "source_url": null,
      "captured_at": null,
      "author": null,
      "contributor": null,
      "id": "adapter_newadapterbymuldb",
      "community": 3,
      "norm_label": "newadapterbymuldb"
    },
    {
      "label": "NewFilteredAdapter",
      "file_type": "code",
      "source_file": "adapter.go",
      "source_location": "adapter.go:223-230",
      "source_url": null,
      "captured_at": null,
      "author": null,
      "contributor": null,
      "id": "adapter_newfilteredadapter",
      "community": 4,
      "norm_label": "newfilteredadapter"
    },
    {
      "label": "NewAdapterByDB",
      "file_type": "code",
      "source_file": "adapter.go",
      "source_location": "adapter.go:233-235",
      "source_url": null,
      "captured_at": null,
      "author": null,
      "contributor": null,
      "id": "adapter_newadapterbydb",
      "community": 3,
      "norm_label": "newadapterbydb"
    },
    {
      "label": "TurnOffAutoMigrate",
      "file_type": "code",
      "source_file": "adapter.go",
      "source_location": "adapter.go:237-246",
      "source_url": null,
      "captured_at": null,
      "author": null,
      "contributor": null,
      "id": "adapter_turnoffautomigrate",
      "community": 6,
      "norm_label": "turnoffautomigrate"
    },
    {
      "label": "NewAdapterByDBWithCustomTable",
      "file_type": "code",
      "source_file": "adapter.go",
      "source_location": "adapter.go:248-262",
      "source_url": null,
      "captured_at": null,
      "author": null,
      "contributor": null,
      "id": "adapter_newadapterbydbwithcustomtable",
      "community": 6,
      "norm_label": "newadapterbydbwithcustomtable"
    },
    {
      "label": "openDBConnection",
      "file_type": "code",
      "source_file": "adapter.go",
      "source_location": "adapter.go:264-270",
      "source_url": null,
      "captured_at": null,
      "author": null,
      "contributor": null,
      "id": "adapter_opendbconnection",
      "community": 10,
      "norm_label": "opendbconnection"
    },
    {
      "label": "Adapter.createDatabase",
      "file_type": "code",
      "source_file": "adapter.go",
      "source_location": "adapter.go:272-292",
      "source_url": null,
      "captured_at": null,
      "author": null,
      "contributor": null,
      "id": "adapter_createdatabase",
      "community": 10,
      "norm_label": "adapter.createdatabase"
    },
    {
      "label": "Adapter.Open",
      "file_type": "code",
      "source_file": "adapter.go",
      "source_location": "adapter.go:294-321",
      "source_url": null,
      "captured_at": null,
      "author": null,
      "contributor": null,
      "id": "adapter_open",
      "community": 4,
      "norm_label": "adapter.open"
    },
    {
      "label": "Adapter.AddLogger",
      "file_type": "code",
      "source_file": "adapter.go",
      "source_location": "adapter.go:324-326",
      "source_url": null,
      "captured_at": null,
      "author": null,
      "contributor": null,
      "id": "adapter_addlogger",
      "community": 8,
      "norm_label": "adapter.addlogger"
    },
    {
      "label": "Adapter.Close",
      "file_type": "code",
      "source_file": "adapter.go",
      "source_location": "adapter.go:328-331",
      "source_url": null,
      "captured_at": null,
      "author": null,
      "contributor": null,
      "id": "adapter_close",
      "community": 8,
      "norm_label": "adapter.close"
    },
    {
      "label": "Adapter.getTableInstance",
      "file_type": "code",
      "source_file": "adapter.go",
      "source_location": "adapter.go:334-336",
      "source_url": null,
      "captured_at": null,
      "author": null,
      "contributor": null,
      "id": "adapter_gettableinstance",
      "community": 9,
      "norm_label": "adapter.gettableinstance"
    },
    {
      "label": "Adapter.getFullTableName",
      "file_type": "code",
      "source_file": "adapter.go",
      "source_location": "adapter.go:338-343",
      "source_url": null,
      "captured_at": null,
      "author": null,
      "contributor": null,
      "id": "adapter_getfulltablename",
      "community": 11,
      "norm_label": "adapter.getfulltablename"
    },
    {
      "label": "Adapter.casbinRuleTable scope",
      "file_type": "code",
      "source_file": "adapter.go",
      "source_location": "adapter.go:345-350",
      "source_url": null,
      "captured_at": null,
      "author": null,
      "contributor": null,
      "id": "adapter_casbinruletable",
      "community": 11,
      "norm_label": "adapter.casbinruletable scope"
    },
    {
      "label": "Adapter.createTable",
      "file_type": "code",
      "source_file": "adapter.go",
      "source_location": "adapter.go:352-378",
      "source_url": null,
      "captured_at": null,
      "author": null,
      "contributor": null,
      "id": "adapter_createtable",
      "community": 6,
      "norm_label": "adapter.createtable"
    },
    {
      "label": "Adapter.dropTable",
      "file_type": "code",
      "source_file": "adapter.go",
      "source_location": "adapter.go:380-387",
      "source_url": null,
      "captured_at": null,
      "author": null,
      "contributor": null,
      "id": "adapter_droptable",
      "community": 9,
      "norm_label": "adapter.droptable"
    },
    {
      "label": "Adapter.truncateTable",
      "file_type": "code",
      "source_file": "adapter.go",
      "source_location": "adapter.go:389-394",
      "source_url": null,
      "captured_at": null,
      "author": null,
      "contributor": null,
      "id": "adapter_truncatetable",
      "community": 11,
      "norm_label": "adapter.truncatetable"
    },
    {
      "label": "loadPolicyLine",
      "file_type": "code",
      "source_file": "adapter.go",
      "source_location": "adapter.go:396-410",
      "source_url": null,
      "captured_at": null,
      "author": null,
      "contributor": null,
      "id": "adapter_loadpolicyline",
      "community": 5,
      "norm_label": "loadpolicyline"
    },
    {
      "label": "Adapter.LoadPolicy",
      "file_type": "code",
      "source_file": "adapter.go",
      "source_location": "adapter.go:413-424",
      "source_url": null,
      "captured_at": null,
      "author": null,
      "contributor": null,
      "id": "adapter_loadpolicy",
      "community": 5,
      "norm_label": "adapter.loadpolicy"
    },
    {
      "label": "Adapter.LoadFilteredPolicy",
      "file_type": "code",
      "source_file": "adapter.go",
      "source_location": "adapter.go:427-445",
      "source_url": null,
      "captured_at": null,
      "author": null,
      "contributor": null,
      "id": "adapter_loadfilteredpolicy",
      "community": 0,
      "norm_label": "adapter.loadfilteredpolicy"
    },
    {
      "label": "Adapter.IsFiltered",
      "file_type": "code",
      "source_file": "adapter.go",
      "source_location": "adapter.go:448-450",
      "source_url": null,
      "captured_at": null,
      "author": null,
      "contributor": null,
      "id": "adapter_isfiltered",
      "community": 0,
      "norm_label": "adapter.isfiltered"
    },
    {
      "label": "Adapter.filterQuery",
      "file_type": "code",
      "source_file": "adapter.go",
      "source_location": "adapter.go:453-484",
      "source_url": null,
      "captured_at": null,
      "author": null,
      "contributor": null,
      "id": "adapter_filterquery",
      "community": 0,
      "norm_label": "adapter.filterquery"
    },
    {
      "label": "Adapter.savePolicyLine",
      "file_type": "code",
      "source_file": "adapter.go",
      "source_location": "adapter.go:486-516",
      "source_url": null,
      "captured_at": null,
      "author": null,
      "contributor": null,
      "id": "adapter_savepolicyline",
      "community": 1,
      "norm_label": "adapter.savepolicyline"
    },
    {
      "label": "Adapter.SavePolicy",
      "file_type": "code",
      "source_file": "adapter.go",
      "source_location": "adapter.go:519-557",
      "source_url": null,
      "captured_at": null,
      "author": null,
      "contributor": null,
      "id": "adapter_savepolicy",
      "community": 0,
      "norm_label": "adapter.savepolicy"
    },
    {
      "label": "Adapter.AddPolicy",
      "file_type": "code",
      "source_file": "adapter.go",
      "source_location": "adapter.go:560-564",
      "source_url": null,
      "captured_at": null,
      "author": null,
      "contributor": null,
      "id": "adapter_addpolicy",
      "community": 5,
      "norm_label": "adapter.addpolicy"
    },
    {
      "label": "Adapter.RemovePolicy",
      "file_type": "code",
      "source_file": "adapter.go",
      "source_location": "adapter.go:567-571",
      "source_url": null,
      "captured_at": null,
      "author": null,
      "contributor": null,
      "id": "adapter_removepolicy",
      "community": 5,
      "norm_label": "adapter.removepolicy"
    },
    {
      "label": "Adapter.AddPolicies",
      "file_type": "code",
      "source_file": "adapter.go",
      "source_location": "adapter.go:574-581",
      "source_url": null,
      "captured_at": null,
      "author": null,
      "contributor": null,
      "id": "adapter_addpolicies",
      "community": 1,
      "norm_label": "adapter.addpolicies"
    },
    {
      "label": "Adapter.RemovePolicies",
      "file_type": "code",
      "source_file": "adapter.go",
      "source_location": "adapter.go:584-594",
      "source_url": null,
      "captured_at": null,
      "author": null,
      "contributor": null,
      "id": "adapter_removepolicies",
      "community": 1,
      "norm_label": "adapter.removepolicies"
    },
    {
      "label": "Adapter.RemoveFilteredPolicy",
      "file_type": "code",
      "source_file": "adapter.go",
      "source_location": "adapter.go:597-637",
      "source_url": null,
      "captured_at": null,
      "author": null,
      "contributor": null,
      "id": "adapter_removefilteredpolicy",
      "community": 9,
      "norm_label": "adapter.removefilteredpolicy"
    },
    {
      "label": "checkQueryField",
      "file_type": "code",
      "source_file": "adapter.go",
      "source_location": "adapter.go:640-647",
      "source_url": null,
      "captured_at": null,
      "author": null,
      "contributor": null,
      "id": "adapter_checkqueryfield",
      "community": 9,
      "norm_label": "checkqueryfield"
    },
    {
      "label": "Adapter.rawDelete",
      "file_type": "code",
      "source_file": "adapter.go",
      "source_location": "adapter.go:649-688",
      "source_url": null,
      "captured_at": null,
      "author": null,
      "contributor": null,
      "id": "adapter_rawdelete",
      "community": 7,
      "norm_label": "adapter.rawdelete"
    },
    {
      "label": "appendWhere",
      "file_type": "code",
      "source_file": "adapter.go",
      "source_location": "adapter.go:690-727",
      "source_url": null,
      "captured_at": null,
      "author": null,
      "contributor": null,
      "id": "adapter_appendwhere",
      "community": 7,
      "norm_label": "appendwhere"
    },
    {
      "label": "Adapter.UpdatePolicy",
      "file_type": "code",
      "source_file": "adapter.go",
      "source_location": "adapter.go:730-734",
      "source_url": null,
      "captured_at": null,
      "author": null,
      "contributor": null,
      "id": "adapter_updatepolicy",
      "community": 1,
      "norm_label": "adapter.updatepolicy"
    },
    {
      "label": "Adapter.UpdatePolicies",
      "file_type": "code",
      "source_file": "adapter.go",
      "source_location": "adapter.go:736-753",
      "source_url": null,
      "captured_at": null,
      "author": null,
      "contributor": null,
      "id": "adapter_updatepolicies",
      "community": 1,
      "norm_label": "adapter.updatepolicies"
    },
    {
      "label": "Adapter.UpdateFilteredPolicies",
      "file_type": "code",
      "source_file": "adapter.go",
      "source_location": "adapter.go:755-816",
      "source_url": null,
      "captured_at": null,
      "author": null,
      "contributor": null,
      "id": "adapter_updatefilteredpolicies",
      "community": 1,
      "norm_label": "adapter.updatefilteredpolicies"
    },
    {
      "label": "CasbinRule.queryString",
      "file_type": "code",
      "source_file": "adapter.go",
      "source_location": "adapter.go:818-856",
      "source_url": null,
      "captured_at": null,
      "author": null,
      "contributor": null,
      "id": "adapter_casbinrule_querystring",
      "community": 7,
      "norm_label": "casbinrule.querystring"
    },
    {
      "label": "CasbinRule.toStringPolicy",
      "file_type": "code",
      "source_file": "adapter.go",
      "source_location": "adapter.go:858-888",
      "source_url": null,
      "captured_at": null,
      "author": null,
      "contributor": null,
      "id": "adapter_casbinrule_tostringpolicy",
      "community": 1,
      "norm_label": "casbinrule.tostringpolicy"
    },
    {
      "label": "initPolicy test helper",
      "file_type": "code",
      "source_file": "adapter_test.go",
      "source_location": "adapter_test.go:86-112",
      "source_url": null,
      "captured_at": null,
      "author": null,
      "contributor": null,
      "id": "adaptertest_initpolicy",
      "community": 0,
      "norm_label": "initpolicy test helper"
    },
    {
      "label": "initAdapter test helper",
      "file_type": "code",
      "source_file": "adapter_test.go",
      "source_location": "adapter_test.go:127-141",
      "source_url": null,
      "captured_at": null,
      "author": null,
      "contributor": null,
      "id": "adaptertest_initadapter",
      "community": 0,
      "norm_label": "initadapter test helper"
    },
    {
      "label": "testSaveLoad",
      "file_type": "code",
      "source_file": "adapter_test.go",
      "source_location": "adapter_test.go:114-125",
      "source_url": null,
      "captured_at": null,
      "author": null,
      "contributor": null,
      "id": "adaptertest_testsaveload",
      "community": 0,
      "norm_label": "testsaveload"
    },
    {
      "label": "testAutoSave",
      "file_type": "code",
      "source_file": "adapter_test.go",
      "source_location": "adapter_test.go:274-311",
      "source_url": null,
      "captured_at": null,
      "author": null,
      "contributor": null,
      "id": "adaptertest_testautosave",
      "community": 5,
      "norm_label": "testautosave"
    },
    {
      "label": "testFilteredPolicy",
      "file_type": "code",
      "source_file": "adapter_test.go",
      "source_location": "adapter_test.go:313-334",
      "source_url": null,
      "captured_at": null,
      "author": null,
      "contributor": null,
      "id": "adaptertest_testfilteredpolicy",
      "community": 0,
      "norm_label": "testfilteredpolicy"
    },
    {
      "label": "TestAdapters",
      "file_type": "code",
      "source_file": "adapter_test.go",
      "source_location": "adapter_test.go:496-607",
      "source_url": null,
      "captured_at": null,
      "author": null,
      "contributor": null,
      "id": "adaptertest_testadapters",
      "community": 0,
      "norm_label": "testadapters"
    },
    {
      "label": "TestAdapterWithMulDb",
      "file_type": "code",
      "source_file": "adapter_test.go",
      "source_location": "adapter_test.go:443-450",
      "source_url": null,
      "captured_at": null,
      "author": null,
      "contributor": null,
      "id": "adaptertest_testadapterwithmuldb",
      "community": 2,
      "norm_label": "testadapterwithmuldb"
    },
    {
      "label": "TestAdapterWithCustomTable",
      "file_type": "code",
      "source_file": "adapter_test.go",
      "source_location": "adapter_test.go:367-391",
      "source_url": null,
      "captured_at": null,
      "author": null,
      "contributor": null,
      "id": "adaptertest_testadapterwithcustomtable",
      "community": 6,
      "norm_label": "testadapterwithcustomtable"
    },
    {
      "label": "TestAdapterWithoutAutoMigrate",
      "file_type": "code",
      "source_file": "adapter_test.go",
      "source_location": "adapter_test.go:393-441",
      "source_url": null,
      "captured_at": null,
      "author": null,
      "contributor": null,
      "id": "adaptertest_testadapterwithoutautomigrate",
      "community": 6,
      "norm_label": "testadapterwithoutautomigrate"
    },
    {
      "label": "TestNilField",
      "file_type": "code",
      "source_file": "adapter_test.go",
      "source_location": "adapter_test.go:255-272",
      "source_url": null,
      "captured_at": null,
      "author": null,
      "contributor": null,
      "id": "adaptertest_testnilfield",
      "community": 4,
      "norm_label": "testnilfield"
    },
    {
      "label": "opens dialect map (no sqlite)",
      "file_type": "code",
      "source_file": "open.go",
      "source_location": "open.go:12-16",
      "source_url": null,
      "captured_at": null,
      "author": null,
      "contributor": null,
      "id": "open_opens_map",
      "community": 10,
      "norm_label": "opens dialect map (no sqlite)"
    },
    {
      "label": "opens dialect map (with sqlite)",
      "file_type": "code",
      "source_file": "open_sqlite3.go",
      "source_location": "open_sqlite3.go:13-18",
      "source_url": null,
      "captured_at": null,
      "author": null,
      "contributor": null,
      "id": "open_sqlite3_opens_map",
      "community": 10,
      "norm_label": "opens dialect map (with sqlite)"
    },
    {
      "label": "gorm-adapter Baseline Reference Spec",
      "file_type": "document",
      "source_file": "docs/superpowers/specs/2026-05-07-gorm-adapter-baseline-design.md",
      "source_location": null,
      "source_url": null,
      "captured_at": "2026-05-07",
      "author": null,
      "contributor": null,
      "id": "2026_05_07_gorm_adapter_baseline_design_baseline_spec",
      "community": 2,
      "norm_label": "gorm-adapter baseline reference spec"
    },
    {
      "label": "Usage Scenario 1 - Persist Casbin policy to a relational database (P1)",
      "file_type": "document",
      "source_file": "docs/superpowers/specs/2026-05-07-gorm-adapter-baseline-design.md",
      "source_location": "lines 22-52",
      "source_url": null,
      "captured_at": "2026-05-07",
      "author": null,
      "contributor": null,
      "id": "2026_05_07_gorm_adapter_baseline_design_usage_scenario_1_persist_policy",
      "community": 5,
      "norm_label": "usage scenario 1 - persist casbin policy to a relational database (p1)"
    },
    {
      "label": "Usage Scenario 2 - Attach Casbin to an existing *gorm.DB (P2)",
      "file_type": "document",
      "source_file": "docs/superpowers/specs/2026-05-07-gorm-adapter-baseline-design.md",
      "source_location": "lines 55-87",
      "source_url": null,
      "captured_at": "2026-05-07",
      "author": null,
      "contributor": null,
      "id": "2026_05_07_gorm_adapter_baseline_design_usage_scenario_2_existing_gorm_db",
      "community": 3,
      "norm_label": "usage scenario 2 - attach casbin to an existing *gorm.db (p2)"
    },
    {
      "label": "Usage Scenario 3 - Filtered policy loading for large policy sets (P3)",
      "file_type": "document",
      "source_file": "docs/superpowers/specs/2026-05-07-gorm-adapter-baseline-design.md",
      "source_location": "lines 90-120",
      "source_url": null,
      "captured_at": "2026-05-07",
      "author": null,
      "contributor": null,
      "id": "2026_05_07_gorm_adapter_baseline_design_usage_scenario_3_filtered_policy_loading",
      "community": 0,
      "norm_label": "usage scenario 3 - filtered policy loading for large policy sets (p3)"
    },
    {
      "label": "AC-001 satisfy persist.Adapter interface",
      "file_type": "document",
      "source_file": "docs/superpowers/specs/2026-05-07-gorm-adapter-baseline-design.md",
      "source_location": "lines 147-149",
      "source_url": null,
      "captured_at": "2026-05-07",
      "author": null,
      "contributor": null,
      "id": "2026_05_07_gorm_adapter_baseline_design_ac_001_persist_adapter",
      "community": 5,
      "norm_label": "ac-001 satisfy persist.adapter interface"
    },
    {
      "label": "AC-002 satisfy persist.FilteredAdapter interface",
      "file_type": "document",
      "source_file": "docs/superpowers/specs/2026-05-07-gorm-adapter-baseline-design.md",
      "source_location": "lines 150-151",
      "source_url": null,
      "captured_at": "2026-05-07",
      "author": null,
      "contributor": null,
      "id": "2026_05_07_gorm_adapter_baseline_design_ac_002_persist_filteredadapter",
      "community": 0,
      "norm_label": "ac-002 satisfy persist.filteredadapter interface"
    },
    {
      "label": "AC-003 satisfy persist.BatchAdapter interface",
      "file_type": "document",
      "source_file": "docs/superpowers/specs/2026-05-07-gorm-adapter-baseline-design.md",
      "source_location": "lines 152-153",
      "source_url": null,
      "captured_at": "2026-05-07",
      "author": null,
      "contributor": null,
      "id": "2026_05_07_gorm_adapter_baseline_design_ac_003_persist_batchadapter",
      "community": 1,
      "norm_label": "ac-003 satisfy persist.batchadapter interface"
    },
    {
      "label": "AC-004 satisfy persist.UpdatableAdapter interface",
      "file_type": "document",
      "source_file": "docs/superpowers/specs/2026-05-07-gorm-adapter-baseline-design.md",
      "source_location": "lines 154-155",
      "source_url": null,
      "captured_at": "2026-05-07",
      "author": null,
      "contributor": null,
      "id": "2026_05_07_gorm_adapter_baseline_design_ac_004_persist_updatableadapter",
      "community": 1,
      "norm_label": "ac-004 satisfy persist.updatableadapter interface"
    },
    {
      "label": "AC-005 supported driver names mysql/postgres/sqlserver/sqlite3-buildtag",
      "file_type": "document",
      "source_file": "docs/superpowers/specs/2026-05-07-gorm-adapter-baseline-design.md",
      "source_location": "lines 156-162",
      "source_url": null,
      "captured_at": "2026-05-07",
      "author": null,
      "contributor": null,
      "id": "2026_05_07_gorm_adapter_baseline_design_ac_005_supported_drivers",
      "community": 4,
      "norm_label": "ac-005 supported driver names mysql/postgres/sqlserver/sqlite3-buildtag"
    },
    {
      "label": "AC-006 default table casbin_rule (singular, post-v3.0.4)",
      "file_type": "document",
      "source_file": "docs/superpowers/specs/2026-05-07-gorm-adapter-baseline-design.md",
      "source_location": "lines 163-165",
      "source_url": null,
      "captured_at": "2026-05-07",
      "author": null,
      "contributor": null,
      "id": "2026_05_07_gorm_adapter_baseline_design_ac_006_default_table_casbin_rule",
      "community": 7,
      "norm_label": "ac-006 default table casbin_rule (singular, post-v3.0.4)"
    },
    {
      "label": "AC-007 AutoMigrate runs unless TurnOffAutoMigrate called",
      "file_type": "document",
      "source_file": "docs/superpowers/specs/2026-05-07-gorm-adapter-baseline-design.md",
      "source_location": "lines 166-168",
      "source_url": null,
      "captured_at": "2026-05-07",
      "author": null,
      "contributor": null,
      "id": "2026_05_07_gorm_adapter_baseline_design_ac_007_automigrate_default_on",
      "community": 6,
      "norm_label": "ac-007 automigrate runs unless turnoffautomigrate called"
    },
    {
      "label": "AC-008 expose six top-level constructors (Minimal Surface)",
      "file_type": "document",
      "source_file": "docs/superpowers/specs/2026-05-07-gorm-adapter-baseline-design.md",
      "source_location": "lines 169-173",
      "source_url": null,
      "captured_at": "2026-05-07",
      "author": null,
      "contributor": null,
      "id": "2026_05_07_gorm_adapter_baseline_design_ac_008_six_constructors",
      "community": 3,
      "norm_label": "ac-008 expose six top-level constructors (minimal surface)"
    },
    {
      "label": "AC-009 expose Open, Close, AddLogger lifecycle methods",
      "file_type": "document",
      "source_file": "docs/superpowers/specs/2026-05-07-gorm-adapter-baseline-design.md",
      "source_location": "lines 174-175",
      "source_url": null,
      "captured_at": "2026-05-07",
      "author": null,
      "contributor": null,
      "id": "2026_05_07_gorm_adapter_baseline_design_ac_009_lifecycle_open_close_addlogger",
      "community": 8,
      "norm_label": "ac-009 expose open, close, addlogger lifecycle methods"
    },
    {
      "label": "AC-010 InitDbResolver returns DbPool with switchDb (multi-DB)",
      "file_type": "document",
      "source_file": "docs/superpowers/specs/2026-05-07-gorm-adapter-baseline-design.md",
      "source_location": "lines 176-179",
      "source_url": null,
      "captured_at": "2026-05-07",
      "author": null,
      "contributor": null,
      "id": "2026_05_07_gorm_adapter_baseline_design_ac_010_initdbresolver_multidb",
      "community": 2,
      "norm_label": "ac-010 initdbresolver returns dbpool with switchdb (multi-db)"
    },
    {
      "label": "AC-011 driver-specific code stays in open.go / open_sqlite3.go",
      "file_type": "document",
      "source_file": "docs/superpowers/specs/2026-05-07-gorm-adapter-baseline-design.md",
      "source_location": "lines 180-182",
      "source_url": null,
      "captured_at": "2026-05-07",
      "author": null,
      "contributor": null,
      "id": "2026_05_07_gorm_adapter_baseline_design_ac_011_driver_isolation_in_open_files",
      "community": 12,
      "norm_label": "ac-011 driver-specific code stays in open.go / open_sqlite3.go"
    },
    {
      "label": "Constructor Convergence on Adapter.Open()",
      "file_type": "rationale",
      "source_file": "docs/superpowers/specs/2026-05-07-gorm-adapter-baseline-design.md",
      "source_location": "lines 233-236",
      "source_url": null,
      "captured_at": "2026-05-07",
      "author": null,
      "contributor": null,
      "id": "2026_05_07_gorm_adapter_baseline_design_constructor_convergence_pattern",
      "community": 4,
      "norm_label": "constructor convergence on adapter.open()"
    },
    {
      "label": "Filter V0-V6 vs CasbinRule V0-V7 asymmetry (V7 storable not filterable)",
      "file_type": "rationale",
      "source_file": "docs/superpowers/specs/2026-05-07-gorm-adapter-baseline-design.md",
      "source_location": "lines 193-196",
      "source_url": null,
      "captured_at": "2026-05-07",
      "author": null,
      "contributor": null,
      "id": "2026_05_07_gorm_adapter_baseline_design_filter_v7_asymmetry",
      "community": 0,
      "norm_label": "filter v0-v6 vs casbinrule v0-v7 asymmetry (v7 storable not filterable)"
    },
    {
      "label": "Drift: README claims glebarez/sqlite, code uses gorm.io/driver/sqlite",
      "file_type": "rationale",
      "source_file": "docs/superpowers/specs/2026-05-07-gorm-adapter-baseline-design.md",
      "source_location": "lines 244-249, 289-297",
      "source_url": null,
      "captured_at": "2026-05-07",
      "author": null,
      "contributor": null,
      "id": "2026_05_07_gorm_adapter_baseline_design_drift_glebarez_vs_gorm_io_sqlite",
      "community": 13,
      "norm_label": "drift: readme claims glebarez/sqlite, code uses gorm.io/driver/sqlite"
    },
    {
      "label": "Drift: SQLite3 support is build-tag-conditional not unconditional",
      "file_type": "rationale",
      "source_file": "docs/superpowers/specs/2026-05-07-gorm-adapter-baseline-design.md",
      "source_location": "lines 299-305",
      "source_url": null,
      "captured_at": "2026-05-07",
      "author": null,
      "contributor": null,
      "id": "2026_05_07_gorm_adapter_baseline_design_drift_sqlite3_buildtag_conditional",
      "community": 14,
      "norm_label": "drift: sqlite3 support is build-tag-conditional not unconditional"
    },
    {
      "label": "Baseline target master @ bc66b93 (2022-11-27)",
      "file_type": "rationale",
      "source_file": "docs/superpowers/specs/2026-05-07-gorm-adapter-baseline-design.md",
      "source_location": "lines 6-9, 257-262",
      "source_url": null,
      "captured_at": "2026-05-07",
      "author": null,
      "contributor": null,
      "id": "2026_05_07_gorm_adapter_baseline_design_baseline_target_bc66b93",
      "community": 2,
      "norm_label": "baseline target master @ bc66b93 (2022-11-27)"
    },
    {
      "label": "Constitution Principle V - Minimal Surface (constructor count cap)",
      "file_type": "rationale",
      "source_file": "docs/superpowers/specs/2026-05-07-gorm-adapter-baseline-design.md",
      "source_location": "lines 169-173",
      "source_url": null,
      "captured_at": "2026-05-07",
      "author": null,
      "contributor": null,
      "id": "2026_05_07_gorm_adapter_baseline_design_principle_v_minimal_surface",
      "community": 3,
      "norm_label": "constitution principle v - minimal surface (constructor count cap)"
    },
    {
      "label": "Constitution Principle II - Cross-Database Parity",
      "file_type": "rationale",
      "source_file": "docs/superpowers/specs/2026-05-07-gorm-adapter-baseline-design.md",
      "source_location": "lines 180-182, 289-305",
      "source_url": null,
      "captured_at": "2026-05-07",
      "author": null,
      "contributor": null,
      "id": "2026_05_07_gorm_adapter_baseline_design_principle_ii_cross_db_parity",
      "community": 12,
      "norm_label": "constitution principle ii - cross-database parity"
    },
    {
      "label": "Filtered SavePolicy must not truncate unrelated rules (data-loss invariant)",
      "file_type": "rationale",
      "source_file": "docs/superpowers/specs/2026-05-07-gorm-adapter-baseline-design.md",
      "source_location": "lines 97-119",
      "source_url": null,
      "captured_at": "2026-05-07",
      "author": null,
      "contributor": null,
      "id": "2026_05_07_gorm_adapter_baseline_design_filtered_save_safety_invariant",
      "community": 0,
      "norm_label": "filtered savepolicy must not truncate unrelated rules (data-loss invariant)"
    },
    {
      "label": "Project file tree index 2026-05-06 snapshot",
      "file_type": "document",
      "source_file": "x_fork.tree-20260506.md",
      "source_location": null,
      "source_url": null,
      "captured_at": "2026-05-08",
      "author": null,
      "contributor": null,
      "id": "x_fork_tree_20260506_project_tree_index",
      "community": 3,
      "norm_label": "project file tree index 2026-05-06 snapshot"
    },
    {
      "label": "Build-tag mutex between open.go and open_sqlite3.go",
      "file_type": "rationale",
      "source_file": "x_fork.tree-20260506.md",
      "source_location": "lines 30-31, 45-48",
      "source_url": null,
      "captured_at": "2026-05-08",
      "author": null,
      "contributor": null,
      "id": "x_fork_tree_20260506_build_tag_mutex_open_files",
      "community": 14,
      "norm_label": "build-tag mutex between open.go and open_sqlite3.go"
    },
    {
      "label": "Six constructors converge on (a *Adapter).Open()",
      "file_type": "rationale",
      "source_file": "x_fork.tree-20260506.md",
      "source_location": "lines 49-52",
      "source_url": null,
      "captured_at": "2026-05-08",
      "author": null,
      "contributor": null,
      "id": "x_fork_tree_20260506_constructor_convergence_open",
      "community": 4,
      "norm_label": "six constructors converge on (a *adapter).open()"
    },
    {
      "label": "open_sqlite3.go uses gorm.io/driver/sqlite while README cites glebarez (drift)",
      "file_type": "rationale",
      "source_file": "x_fork.tree-20260506.md",
      "source_location": "line 31",
      "source_url": null,
      "captured_at": "2026-05-08",
      "author": null,
      "contributor": null,
      "id": "x_fork_tree_20260506_open_sqlite3_glebarez_drift_note",
      "community": 13,
      "norm_label": "open_sqlite3.go uses gorm.io/driver/sqlite while readme cites glebarez (drift)"
    }
  ],
  "links": [
    {
      "relation": "references",
      "confidence": "EXTRACTED",
      "confidence_score": 1.0,
      "source_file": "adapter.go",
      "source_location": "adapter.go:486",
      "weight": 1.0,
      "source": "adapter_casbinrule",
      "target": "adapter_savepolicyline"
    },
    {
      "relation": "references",
      "confidence": "EXTRACTED",
      "confidence_score": 1.0,
      "source_file": "adapter.go",
      "source_location": "adapter.go:396",
      "weight": 1.0,
      "source": "adapter_casbinrule",
      "target": "adapter_loadpolicyline"
    },
    {
      "relation": "references",
      "confidence": "EXTRACTED",
      "confidence_score": 1.0,
      "source_file": "adapter.go",
      "source_location": "adapter.go:649",
      "weight": 1.0,
      "source": "adapter_casbinrule",
      "target": "adapter_rawdelete"
    },
    {
      "relation": "references",
      "confidence": "EXTRACTED",
      "confidence_score": 1.0,
      "source_file": "adapter.go",
      "source_location": "adapter.go:690",
      "weight": 1.0,
      "source": "adapter_casbinrule",
      "target": "adapter_appendwhere"
    },
    {
      "relation": "references",
      "confidence": "EXTRACTED",
      "confidence_score": 1.0,
      "source_file": "docs/superpowers/specs/2026-05-07-gorm-adapter-baseline-design.md",
      "source_location": "lines 47-48",
      "weight": 1.0,
      "source": "adapter_casbinrule",
      "target": "2026_05_07_gorm_adapter_baseline_design_usage_scenario_1_persist_policy"
    },
    {
      "relation": "references",
      "confidence": "EXTRACTED",
      "confidence_score": 1.0,
      "source_file": "docs/superpowers/specs/2026-05-07-gorm-adapter-baseline-design.md",
      "source_location": "lines 163-165",
      "weight": 1.0,
      "source": "adapter_casbinrule",
      "target": "2026_05_07_gorm_adapter_baseline_design_ac_006_default_table_casbin_rule"
    },
    {
      "relation": "references",
      "confidence": "EXTRACTED",
      "confidence_score": 1.0,
      "source_file": "docs/superpowers/specs/2026-05-07-gorm-adapter-baseline-design.md",
      "source_location": "lines 191-193",
      "weight": 1.0,
      "source": "adapter_casbinrule",
      "target": "2026_05_07_gorm_adapter_baseline_design_baseline_spec"
    },
    {
      "relation": "rationale_for",
      "confidence": "EXTRACTED",
      "confidence_score": 1.0,
      "source_file": "docs/superpowers/specs/2026-05-07-gorm-adapter-baseline-design.md",
      "source_location": "lines 193-196",
      "weight": 1.0,
      "source": "adapter_casbinrule",
      "target": "2026_05_07_gorm_adapter_baseline_design_filter_v7_asymmetry"
    },
    {
      "relation": "references",
      "confidence": "EXTRACTED",
      "confidence_score": 1.0,
      "source_file": "x_fork.tree-20260506.md",
      "source_location": "lines 16, 65",
      "weight": 1.0,
      "source": "adapter_casbinrule",
      "target": "x_fork_tree_20260506_project_tree_index"
    },
    {
      "relation": "references",
      "confidence": "EXTRACTED",
      "confidence_score": 1.0,
      "source_file": "adapter.go",
      "source_location": "adapter.go:430",
      "weight": 1.0,
      "source": "adapter_filter",
      "target": "adapter_loadfilteredpolicy"
    },
    {
      "relation": "references",
      "confidence": "EXTRACTED",
      "confidence_score": 1.0,
      "source_file": "adapter.go",
      "source_location": "adapter.go:453",
      "weight": 1.0,
      "source": "adapter_filter",
      "target": "adapter_filterquery"
    },
    {
      "relation": "references",
      "confidence": "EXTRACTED",
      "confidence_score": 1.0,
      "source_file": "adapter_test.go",
      "source_location": "adapter_test.go:320-332",
      "weight": 1.0,
      "source": "adapter_filter",
      "target": "adaptertest_testfilteredpolicy"
    },
    {
      "relation": "references",
      "confidence": "EXTRACTED",
      "confidence_score": 1.0,
      "source_file": "docs/superpowers/specs/2026-05-07-gorm-adapter-baseline-design.md",
      "source_location": "lines 95-119",
      "weight": 1.0,
      "source": "adapter_filter",
      "target": "2026_05_07_gorm_adapter_baseline_design_usage_scenario_3_filtered_policy_loading"
    },
    {
      "relation": "references",
      "confidence": "EXTRACTED",
      "confidence_score": 1.0,
      "source_file": "docs/superpowers/specs/2026-05-07-gorm-adapter-baseline-design.md",
      "source_location": "lines 194-197",
      "weight": 1.0,
      "source": "adapter_filter",
      "target": "2026_05_07_gorm_adapter_baseline_design_baseline_spec"
    },
    {
      "relation": "rationale_for",
      "confidence": "EXTRACTED",
      "confidence_score": 1.0,
      "source_file": "docs/superpowers/specs/2026-05-07-gorm-adapter-baseline-design.md",
      "source_location": "lines 193-196",
      "weight": 1.0,
      "source": "adapter_filter",
      "target": "2026_05_07_gorm_adapter_baseline_design_filter_v7_asymmetry"
    },
    {
      "relation": "references",
      "confidence": "EXTRACTED",
      "confidence_score": 1.0,
      "source_file": "x_fork.tree-20260506.md",
      "source_location": "line 16",
      "weight": 1.0,
      "source": "adapter_filter",
      "target": "x_fork_tree_20260506_project_tree_index"
    },
    {
      "relation": "references",
      "confidence": "EXTRACTED",
      "confidence_score": 1.0,
      "source_file": "adapter.go",
      "source_location": "adapter.go:68",
      "weight": 1.0,
      "source": "adapter_adapter",
      "target": "adapter_finalizer"
    },
    {
      "relation": "references",
      "confidence": "EXTRACTED",
      "confidence_score": 1.0,
      "source_file": "docs/superpowers/specs/2026-05-07-gorm-adapter-baseline-design.md",
      "source_location": "lines 147-149",
      "weight": 1.0,
      "source": "adapter_adapter",
      "target": "2026_05_07_gorm_adapter_baseline_design_ac_001_persist_adapter"
    },
    {
      "relation": "references",
      "confidence": "EXTRACTED",
      "confidence_score": 1.0,
      "source_file": "docs/superpowers/specs/2026-05-07-gorm-adapter-baseline-design.md",
      "source_location": "lines 187-190",
      "weight": 1.0,
      "source": "adapter_adapter",
      "target": "2026_05_07_gorm_adapter_baseline_design_baseline_spec"
    },
    {
      "relation": "references",
      "confidence": "EXTRACTED",
      "confidence_score": 1.0,
      "source_file": "x_fork.tree-20260506.md",
      "source_location": "lines 16, 62",
      "weight": 1.0,
      "source": "adapter_adapter",
      "target": "x_fork_tree_20260506_project_tree_index"
    },
    {
      "relation": "references",
      "confidence": "EXTRACTED",
      "confidence_score": 1.0,
      "source_file": "adapter.go",
      "source_location": "adapter.go:164",
      "weight": 1.0,
      "source": "adapter_finalizer",
      "target": "adapter_newadapter"
    },
    {
      "relation": "calls",
      "confidence": "EXTRACTED",
      "confidence_score": 1.0,
      "source_file": "adapter.go",
      "source_location": "adapter.go:329",
      "weight": 1.0,
      "source": "adapter_finalizer",
      "target": "adapter_close"
    },
    {
      "relation": "references",
      "confidence": "EXTRACTED",
      "confidence_score": 1.0,
      "source_file": "adapter.go",
      "source_location": "adapter.go:204-209",
      "weight": 1.0,
      "source": "adapter_specificpolicy",
      "target": "adapter_initdbresolver"
    },
    {
      "relation": "shares_data_with",
      "confidence": "EXTRACTED",
      "confidence_score": 1.0,
      "source_file": "adapter.go",
      "source_location": "adapter.go:86-90",
      "weight": 1.0,
      "source": "adapter_specificpolicy",
      "target": "adapter_dbpool"
    },
    {
      "relation": "references",
      "confidence": "EXTRACTED",
      "confidence_score": 1.0,
      "source_file": "docs/superpowers/specs/2026-05-07-gorm-adapter-baseline-design.md",
      "source_location": "lines 201-202",
      "weight": 1.0,
      "source": "adapter_specificpolicy",
      "target": "2026_05_07_gorm_adapter_baseline_design_baseline_spec"
    },
    {
      "relation": "references",
      "confidence": "EXTRACTED",
      "confidence_score": 1.0,
      "source_file": "adapter.go",
      "source_location": "adapter.go:211",
      "weight": 1.0,
      "source": "adapter_dbpool",
      "target": "adapter_initdbresolver"
    },
    {
      "relation": "references",
      "confidence": "EXTRACTED",
      "confidence_score": 1.0,
      "source_file": "adapter.go",
      "source_location": "adapter.go:92",
      "weight": 1.0,
      "source": "adapter_dbpool",
      "target": "adapter_dbpool_switchdb"
    },
    {
      "relation": "references",
      "confidence": "EXTRACTED",
      "confidence_score": 1.0,
      "source_file": "docs/superpowers/specs/2026-05-07-gorm-adapter-baseline-design.md",
      "source_location": "lines 176-179",
      "weight": 1.0,
      "source": "adapter_dbpool",
      "target": "2026_05_07_gorm_adapter_baseline_design_ac_010_initdbresolver_multidb"
    },
    {
      "relation": "references",
      "confidence": "EXTRACTED",
      "confidence_score": 1.0,
      "source_file": "docs/superpowers/specs/2026-05-07-gorm-adapter-baseline-design.md",
      "source_location": "lines 198-200",
      "weight": 1.0,
      "source": "adapter_dbpool",
      "target": "2026_05_07_gorm_adapter_baseline_design_baseline_spec"
    },
    {
      "relation": "references",
      "confidence": "EXTRACTED",
      "confidence_score": 1.0,
      "source_file": "x_fork.tree-20260506.md",
      "source_location": "line 16",
      "weight": 1.0,
      "source": "adapter_dbpool",
      "target": "x_fork_tree_20260506_project_tree_index"
    },
    {
      "relation": "calls",
      "confidence": "EXTRACTED",
      "confidence_score": 1.0,
      "source_file": "adapter.go",
      "source_location": "adapter.go:216",
      "weight": 1.0,
      "source": "adapter_dbpool_switchdb",
      "target": "adapter_newadapterbymuldb"
    },
    {
      "relation": "calls",
      "confidence": "EXTRACTED",
      "confidence_score": 1.0,
      "source_file": "adapter.go",
      "source_location": "adapter.go:158",
      "weight": 1.0,
      "source": "adapter_newadapter",
      "target": "adapter_open"
    },
    {
      "relation": "calls",
      "confidence": "EXTRACTED",
      "confidence_score": 1.0,
      "source_file": "adapter.go",
      "source_location": "adapter.go:224",
      "weight": 1.0,
      "source": "adapter_newadapter",
      "target": "adapter_newfilteredadapter"
    },
    {
      "relation": "calls",
      "confidence": "EXTRACTED",
      "confidence_score": 1.0,
      "source_file": "adapter_test.go",
      "source_location": "adapter_test.go:129",
      "weight": 1.0,
      "source": "adapter_newadapter",
      "target": "adaptertest_initadapter"
    },
    {
      "relation": "calls",
      "confidence": "EXTRACTED",
      "confidence_score": 1.0,
      "source_file": "adapter_test.go",
      "source_location": "adapter_test.go:445-446",
      "weight": 1.0,
      "source": "adapter_newadapter",
      "target": "adaptertest_testadapterwithmuldb"
    },
    {
      "relation": "calls",
      "confidence": "EXTRACTED",
      "confidence_score": 1.0,
      "source_file": "adapter_test.go",
      "source_location": "adapter_test.go:256",
      "weight": 1.0,
      "source": "adapter_newadapter",
      "target": "adaptertest_testnilfield"
    },
    {
      "relation": "references",
      "confidence": "EXTRACTED",
      "confidence_score": 1.0,
      "source_file": "docs/superpowers/specs/2026-05-07-gorm-adapter-baseline-design.md",
      "source_location": "lines 41-45",
      "weight": 1.0,
      "source": "adapter_newadapter",
      "target": "2026_05_07_gorm_adapter_baseline_design_usage_scenario_1_persist_policy"
    },
    {
      "relation": "references",
      "confidence": "EXTRACTED",
      "confidence_score": 1.0,
      "source_file": "docs/superpowers/specs/2026-05-07-gorm-adapter-baseline-design.md",
      "source_location": "lines 156-162",
      "weight": 1.0,
      "source": "adapter_newadapter",
      "target": "2026_05_07_gorm_adapter_baseline_design_ac_005_supported_drivers"
    },
    {
      "relation": "references",
      "confidence": "EXTRACTED",
      "confidence_score": 1.0,
      "source_file": "docs/superpowers/specs/2026-05-07-gorm-adapter-baseline-design.md",
      "source_location": "lines 169-173",
      "weight": 1.0,
      "source": "adapter_newadapter",
      "target": "2026_05_07_gorm_adapter_baseline_design_ac_008_six_constructors"
    },
    {
      "relation": "references",
      "confidence": "EXTRACTED",
      "confidence_score": 1.0,
      "source_file": "docs/superpowers/specs/2026-05-07-gorm-adapter-baseline-design.md",
      "source_location": "lines 233-236",
      "weight": 1.0,
      "source": "adapter_newadapter",
      "target": "2026_05_07_gorm_adapter_baseline_design_constructor_convergence_pattern"
    },
    {
      "relation": "references",
      "confidence": "EXTRACTED",
      "confidence_score": 1.0,
      "source_file": "x_fork.tree-20260506.md",
      "source_location": "lines 49-52, 69",
      "weight": 1.0,
      "source": "adapter_newadapter",
      "target": "x_fork_tree_20260506_project_tree_index"
    },
    {
      "relation": "references",
      "confidence": "EXTRACTED",
      "confidence_score": 1.0,
      "source_file": "x_fork.tree-20260506.md",
      "source_location": "lines 49-52",
      "weight": 1.0,
      "source": "adapter_newadapter",
      "target": "x_fork_tree_20260506_constructor_convergence_open"
    },
    {
      "relation": "calls",
      "confidence": "EXTRACTED",
      "confidence_score": 1.0,
      "source_file": "adapter.go",
      "source_location": "adapter.go:181",
      "weight": 1.0,
      "source": "adapter_newadapterbydbusetablename",
      "target": "adapter_casbinruletable"
    },
    {
      "relation": "calls",
      "confidence": "EXTRACTED",
      "confidence_score": 1.0,
      "source_file": "adapter.go",
      "source_location": "adapter.go:183",
      "weight": 1.0,
      "source": "adapter_newadapterbydbusetablename",
      "target": "adapter_createtable"
    },
    {
      "relation": "calls",
      "confidence": "EXTRACTED",
      "confidence_score": 1.0,
      "source_file": "adapter.go",
      "source_location": "adapter.go:234",
      "weight": 1.0,
      "source": "adapter_newadapterbydbusetablename",
      "target": "adapter_newadapterbydb"
    },
    {
      "relation": "calls",
      "confidence": "EXTRACTED",
      "confidence_score": 1.0,
      "source_file": "adapter.go",
      "source_location": "adapter.go:261",
      "weight": 1.0,
      "source": "adapter_newadapterbydbusetablename",
      "target": "adapter_newadapterbydbwithcustomtable"
    },
    {
      "relation": "calls",
      "confidence": "EXTRACTED",
      "confidence_score": 1.0,
      "source_file": "adapter.go",
      "source_location": "adapter.go:218",
      "weight": 1.0,
      "source": "adapter_newadapterbydbusetablename",
      "target": "adapter_newadapterbymuldb"
    },
    {
      "relation": "references",
      "confidence": "EXTRACTED",
      "confidence_score": 1.0,
      "source_file": "docs/superpowers/specs/2026-05-07-gorm-adapter-baseline-design.md",
      "source_location": "lines 77-79",
      "weight": 1.0,
      "source": "adapter_newadapterbydbusetablename",
      "target": "2026_05_07_gorm_adapter_baseline_design_usage_scenario_2_existing_gorm_db"
    },
    {
      "relation": "references",
      "confidence": "EXTRACTED",
      "confidence_score": 1.0,
      "source_file": "docs/superpowers/specs/2026-05-07-gorm-adapter-baseline-design.md",
      "source_location": "lines 169-173",
      "weight": 1.0,
      "source": "adapter_newadapterbydbusetablename",
      "target": "2026_05_07_gorm_adapter_baseline_design_ac_008_six_constructors"
    },
    {
      "relation": "references",
      "confidence": "EXTRACTED",
      "confidence_score": 1.0,
      "source_file": "docs/superpowers/specs/2026-05-07-gorm-adapter-baseline-design.md",
      "source_location": "lines 233-236",
      "weight": 1.0,
      "source": "adapter_newadapterbydbusetablename",
      "target": "2026_05_07_gorm_adapter_baseline_design_constructor_convergence_pattern"
    },
    {
      "relation": "references",
      "confidence": "EXTRACTED",
      "confidence_score": 1.0,
      "source_file": "x_fork.tree-20260506.md",
      "source_location": "lines 49-52, 66",
      "weight": 1.0,
      "source": "adapter_newadapterbydbusetablename",
      "target": "x_fork_tree_20260506_project_tree_index"
    },
    {
      "relation": "references",
      "confidence": "EXTRACTED",
      "confidence_score": 1.0,
      "source_file": "adapter_test.go",
      "source_location": "adapter_test.go:456",
      "weight": 1.0,
      "source": "adapter_initdbresolver",
      "target": "adaptertest_testadapterwithmuldb"
    },
    {
      "relation": "references",
      "confidence": "EXTRACTED",
      "confidence_score": 1.0,
      "source_file": "docs/superpowers/specs/2026-05-07-gorm-adapter-baseline-design.md",
      "source_location": "lines 176-179",
      "weight": 1.0,
      "source": "adapter_initdbresolver",
      "target": "2026_05_07_gorm_adapter_baseline_design_ac_010_initdbresolver_multidb"
    },
    {
      "relation": "references",
      "confidence": "EXTRACTED",
      "confidence_score": 1.0,
      "source_file": "docs/superpowers/specs/2026-05-07-gorm-adapter-baseline-design.md",
      "source_location": "lines 169-173",
      "weight": 1.0,
      "source": "adapter_newadapterbymuldb",
      "target": "2026_05_07_gorm_adapter_baseline_design_ac_008_six_constructors"
    },
    {
      "relation": "references",
      "confidence": "EXTRACTED",
      "confidence_score": 1.0,
      "source_file": "docs/superpowers/specs/2026-05-07-gorm-adapter-baseline-design.md",
      "source_location": "lines 176-179",
      "weight": 1.0,
      "source": "adapter_newadapterbymuldb",
      "target": "2026_05_07_gorm_adapter_baseline_design_ac_010_initdbresolver_multidb"
    },
    {
      "relation": "references",
      "confidence": "EXTRACTED",
      "confidence_score": 1.0,
      "source_file": "x_fork.tree-20260506.md",
      "source_location": "lines 49-52",
      "weight": 1.0,
      "source": "adapter_newadapterbymuldb",
      "target": "x_fork_tree_20260506_project_tree_index"
    },
    {
      "relation": "references",
      "confidence": "EXTRACTED",
      "confidence_score": 1.0,
      "source_file": "docs/superpowers/specs/2026-05-07-gorm-adapter-baseline-design.md",
      "source_location": "lines 110-113",
      "weight": 1.0,
      "source": "adapter_newfilteredadapter",
      "target": "2026_05_07_gorm_adapter_baseline_design_usage_scenario_3_filtered_policy_loading"
    },
    {
      "relation": "references",
      "confidence": "EXTRACTED",
      "confidence_score": 1.0,
      "source_file": "docs/superpowers/specs/2026-05-07-gorm-adapter-baseline-design.md",
      "source_location": "lines 156-162",
      "weight": 1.0,
      "source": "adapter_newfilteredadapter",
      "target": "2026_05_07_gorm_adapter_baseline_design_ac_005_supported_drivers"
    },
    {
      "relation": "references",
      "confidence": "EXTRACTED",
      "confidence_score": 1.0,
      "source_file": "docs/superpowers/specs/2026-05-07-gorm-adapter-baseline-design.md",
      "source_location": "lines 169-173",
      "weight": 1.0,
      "source": "adapter_newfilteredadapter",
      "target": "2026_05_07_gorm_adapter_baseline_design_ac_008_six_constructors"
    },
    {
      "relation": "references",
      "confidence": "EXTRACTED",
      "confidence_score": 1.0,
      "source_file": "x_fork.tree-20260506.md",
      "source_location": "lines 49-52",
      "weight": 1.0,
      "source": "adapter_newfilteredadapter",
      "target": "x_fork_tree_20260506_project_tree_index"
    },
    {
      "relation": "references",
      "confidence": "EXTRACTED",
      "confidence_score": 1.0,
      "source_file": "docs/superpowers/specs/2026-05-07-gorm-adapter-baseline-design.md",
      "source_location": "lines 74-76",
      "weight": 1.0,
      "source": "adapter_newadapterbydb",
      "target": "2026_05_07_gorm_adapter_baseline_design_usage_scenario_2_existing_gorm_db"
    },
    {
      "relation": "references",
      "confidence": "EXTRACTED",
      "confidence_score": 1.0,
      "source_file": "docs/superpowers/specs/2026-05-07-gorm-adapter-baseline-design.md",
      "source_location": "lines 169-173",
      "weight": 1.0,
      "source": "adapter_newadapterbydb",
      "target": "2026_05_07_gorm_adapter_baseline_design_ac_008_six_constructors"
    },
    {
      "relation": "references",
      "confidence": "EXTRACTED",
      "confidence_score": 1.0,
      "source_file": "docs/superpowers/specs/2026-05-07-gorm-adapter-baseline-design.md",
      "source_location": "lines 233-236",
      "weight": 1.0,
      "source": "adapter_newadapterbydb",
      "target": "2026_05_07_gorm_adapter_baseline_design_constructor_convergence_pattern"
    },
    {
      "relation": "references",
      "confidence": "EXTRACTED",
      "confidence_score": 1.0,
      "source_file": "x_fork.tree-20260506.md",
      "source_location": "lines 49-52",
      "weight": 1.0,
      "source": "adapter_newadapterbydb",
      "target": "x_fork_tree_20260506_project_tree_index"
    },
    {
      "relation": "shares_data_with",
      "confidence": "INFERRED",
      "confidence_score": 0.85,
      "source_file": "adapter.go",
      "source_location": null,
      "weight": 1.0,
      "source": "adapter_turnoffautomigrate",
      "target": "adapter_createtable"
    },
    {
      "relation": "calls",
      "confidence": "EXTRACTED",
      "confidence_score": 1.0,
      "source_file": "adapter_test.go",
      "source_location": "adapter_test.go:203",
      "weight": 1.0,
      "source": "adapter_turnoffautomigrate",
      "target": "adaptertest_testadapterwithoutautomigrate"
    },
    {
      "relation": "references",
      "confidence": "EXTRACTED",
      "confidence_score": 1.0,
      "source_file": "docs/superpowers/specs/2026-05-07-gorm-adapter-baseline-design.md",
      "source_location": "lines 84-86",
      "weight": 1.0,
      "source": "adapter_turnoffautomigrate",
      "target": "2026_05_07_gorm_adapter_baseline_design_usage_scenario_2_existing_gorm_db"
    },
    {
      "relation": "references",
      "confidence": "EXTRACTED",
      "confidence_score": 1.0,
      "source_file": "docs/superpowers/specs/2026-05-07-gorm-adapter-baseline-design.md",
      "source_location": "lines 166-168",
      "weight": 1.0,
      "source": "adapter_turnoffautomigrate",
      "target": "2026_05_07_gorm_adapter_baseline_design_ac_007_automigrate_default_on"
    },
    {
      "relation": "shares_data_with",
      "confidence": "INFERRED",
      "confidence_score": 0.85,
      "source_file": "adapter.go",
      "source_location": null,
      "weight": 1.0,
      "source": "adapter_newadapterbydbwithcustomtable",
      "target": "adapter_createtable"
    },
    {
      "relation": "references",
      "confidence": "INFERRED",
      "confidence_score": 0.85,
      "source_file": "adapter_test.go",
      "source_location": "adapter_test.go:170",
      "weight": 1.0,
      "source": "adapter_newadapterbydbwithcustomtable",
      "target": "adaptertest_testadapterwithcustomtable"
    },
    {
      "relation": "calls",
      "confidence": "EXTRACTED",
      "confidence_score": 1.0,
      "source_file": "adapter_test.go",
      "source_location": "adapter_test.go:217",
      "weight": 1.0,
      "source": "adapter_newadapterbydbwithcustomtable",
      "target": "adaptertest_testadapterwithoutautomigrate"
    },
    {
      "relation": "references",
      "confidence": "EXTRACTED",
      "confidence_score": 1.0,
      "source_file": "docs/superpowers/specs/2026-05-07-gorm-adapter-baseline-design.md",
      "source_location": "lines 80-83",
      "weight": 1.0,
      "source": "adapter_newadapterbydbwithcustomtable",
      "target": "2026_05_07_gorm_adapter_baseline_design_usage_scenario_2_existing_gorm_db"
    },
    {
      "relation": "references",
      "confidence": "EXTRACTED",
      "confidence_score": 1.0,
      "source_file": "docs/superpowers/specs/2026-05-07-gorm-adapter-baseline-design.md",
      "source_location": "lines 169-173",
      "weight": 1.0,
      "source": "adapter_newadapterbydbwithcustomtable",
      "target": "2026_05_07_gorm_adapter_baseline_design_ac_008_six_constructors"
    },
    {
      "relation": "references",
      "confidence": "EXTRACTED",
      "confidence_score": 1.0,
      "source_file": "x_fork.tree-20260506.md",
      "source_location": "lines 49-52, 70",
      "weight": 1.0,
      "source": "adapter_newadapterbydbwithcustomtable",
      "target": "x_fork_tree_20260506_project_tree_index"
    },
    {
      "relation": "calls",
      "confidence": "EXTRACTED",
      "confidence_score": 1.0,
      "source_file": "adapter.go",
      "source_location": "adapter.go:299-312",
      "weight": 1.0,
      "source": "adapter_opendbconnection",
      "target": "adapter_open"
    },
    {
      "relation": "calls",
      "confidence": "EXTRACTED",
      "confidence_score": 1.0,
      "source_file": "adapter.go",
      "source_location": "adapter.go:274",
      "weight": 1.0,
      "source": "adapter_opendbconnection",
      "target": "adapter_createdatabase"
    },
    {
      "relation": "references",
      "confidence": "EXTRACTED",
      "confidence_score": 1.0,
      "source_file": "adapter.go",
      "source_location": "adapter.go:265",
      "weight": 1.0,
      "source": "adapter_opendbconnection",
      "target": "open_opens_map"
    },
    {
      "relation": "references",
      "confidence": "EXTRACTED",
      "confidence_score": 1.0,
      "source_file": "adapter.go",
      "source_location": "adapter.go:265",
      "weight": 1.0,
      "source": "adapter_opendbconnection",
      "target": "open_sqlite3_opens_map"
    },
    {
      "relation": "calls",
      "confidence": "EXTRACTED",
      "confidence_score": 1.0,
      "source_file": "adapter.go",
      "source_location": "adapter.go:304",
      "weight": 1.0,
      "source": "adapter_createdatabase",
      "target": "adapter_open"
    },
    {
      "relation": "calls",
      "confidence": "EXTRACTED",
      "confidence_score": 1.0,
      "source_file": "adapter.go",
      "source_location": "adapter.go:319",
      "weight": 1.0,
      "source": "adapter_open",
      "target": "adapter_casbinruletable"
    },
    {
      "relation": "calls",
      "confidence": "EXTRACTED",
      "confidence_score": 1.0,
      "source_file": "adapter.go",
      "source_location": "adapter.go:320",
      "weight": 1.0,
      "source": "adapter_open",
      "target": "adapter_createtable"
    },
    {
      "relation": "references",
      "confidence": "EXTRACTED",
      "confidence_score": 1.0,
      "source_file": "docs/superpowers/specs/2026-05-07-gorm-adapter-baseline-design.md",
      "source_location": "lines 174-175",
      "weight": 1.0,
      "source": "adapter_open",
      "target": "2026_05_07_gorm_adapter_baseline_design_ac_009_lifecycle_open_close_addlogger"
    },
    {
      "relation": "rationale_for",
      "confidence": "EXTRACTED",
      "confidence_score": 1.0,
      "source_file": "docs/superpowers/specs/2026-05-07-gorm-adapter-baseline-design.md",
      "source_location": "lines 233-236",
      "weight": 1.0,
      "source": "adapter_open",
      "target": "2026_05_07_gorm_adapter_baseline_design_constructor_convergence_pattern"
    },
    {
      "relation": "references",
      "confidence": "EXTRACTED",
      "confidence_score": 1.0,
      "source_file": "x_fork.tree-20260506.md",
      "source_location": "lines 49-52",
      "weight": 1.0,
      "source": "adapter_open",
      "target": "x_fork_tree_20260506_project_tree_index"
    },
    {
      "relation": "rationale_for",
      "confidence": "EXTRACTED",
      "confidence_score": 1.0,
      "source_file": "x_fork.tree-20260506.md",
      "source_location": "lines 49-52",
      "weight": 1.0,
      "source": "adapter_open",
      "target": "x_fork_tree_20260506_constructor_convergence_open"
    },
    {
      "relation": "references",
      "confidence": "EXTRACTED",
      "confidence_score": 1.0,
      "source_file": "docs/superpowers/specs/2026-05-07-gorm-adapter-baseline-design.md",
      "source_location": "lines 174-175",
      "weight": 1.0,
      "source": "adapter_addlogger",
      "target": "2026_05_07_gorm_adapter_baseline_design_ac_009_lifecycle_open_close_addlogger"
    },
    {
      "relation": "references",
      "confidence": "EXTRACTED",
      "confidence_score": 1.0,
      "source_file": "docs/superpowers/specs/2026-05-07-gorm-adapter-baseline-design.md",
      "source_location": "lines 174-175",
      "weight": 1.0,
      "source": "adapter_close",
      "target": "2026_05_07_gorm_adapter_baseline_design_ac_009_lifecycle_open_close_addlogger"
    },
    {
      "relation": "calls",
      "confidence": "EXTRACTED",
      "confidence_score": 1.0,
      "source_file": "adapter.go",
      "source_location": "adapter.go:364",
      "weight": 1.0,
      "source": "adapter_gettableinstance",
      "target": "adapter_createtable"
    },
    {
      "relation": "calls",
      "confidence": "EXTRACTED",
      "confidence_score": 1.0,
      "source_file": "adapter.go",
      "source_location": "adapter.go:383",
      "weight": 1.0,
      "source": "adapter_gettableinstance",
      "target": "adapter_droptable"
    },
    {
      "relation": "calls",
      "confidence": "EXTRACTED",
      "confidence_score": 1.0,
      "source_file": "adapter.go",
      "source_location": "adapter.go:598",
      "weight": 1.0,
      "source": "adapter_gettableinstance",
      "target": "adapter_removefilteredpolicy"
    },
    {
      "relation": "calls",
      "confidence": "EXTRACTED",
      "confidence_score": 1.0,
      "source_file": "adapter.go",
      "source_location": "adapter.go:487",
      "weight": 1.0,
      "source": "adapter_gettableinstance",
      "target": "adapter_savepolicyline"
    },
    {
      "relation": "calls",
      "confidence": "EXTRACTED",
      "confidence_score": 1.0,
      "source_file": "adapter.go",
      "source_location": "adapter.go:686",
      "weight": 1.0,
      "source": "adapter_gettableinstance",
      "target": "adapter_rawdelete"
    },
    {
      "relation": "calls",
      "confidence": "EXTRACTED",
      "confidence_score": 1.0,
      "source_file": "adapter.go",
      "source_location": "adapter.go:757",
      "weight": 1.0,
      "source": "adapter_gettableinstance",
      "target": "adapter_updatefilteredpolicies"
    },
    {
      "relation": "calls",
      "confidence": "EXTRACTED",
      "confidence_score": 1.0,
      "source_file": "adapter.go",
      "source_location": "adapter.go:369",
      "weight": 1.0,
      "source": "adapter_getfulltablename",
      "target": "adapter_createtable"
    },
    {
      "relation": "calls",
      "confidence": "EXTRACTED",
      "confidence_score": 1.0,
      "source_file": "adapter.go",
      "source_location": "adapter.go:391-393",
      "weight": 1.0,
      "source": "adapter_getfulltablename",
      "target": "adapter_truncatetable"
    },
    {
      "relation": "calls",
      "confidence": "EXTRACTED",
      "confidence_score": 1.0,
      "source_file": "adapter.go",
      "source_location": "adapter.go:347",
      "weight": 1.0,
      "source": "adapter_getfulltablename",
      "target": "adapter_casbinruletable"
    },
    {
      "relation": "references",
      "confidence": "INFERRED",
      "confidence_score": 0.85,
      "source_file": "docs/superpowers/specs/2026-05-07-gorm-adapter-baseline-design.md",
      "source_location": "lines 166-168",
      "weight": 1.0,
      "source": "adapter_createtable",
      "target": "2026_05_07_gorm_adapter_baseline_design_ac_007_automigrate_default_on"
    },
    {
      "relation": "calls",
      "confidence": "EXTRACTED",
      "confidence_score": 1.0,
      "source_file": "adapter.go",
      "source_location": "adapter.go:520",
      "weight": 1.0,
      "source": "adapter_truncatetable",
      "target": "adapter_savepolicy"
    },
    {
      "relation": "calls",
      "confidence": "EXTRACTED",
      "confidence_score": 1.0,
      "source_file": "adapter.go",
      "source_location": "adapter.go:420",
      "weight": 1.0,
      "source": "adapter_loadpolicyline",
      "target": "adapter_loadpolicy"
    },
    {
      "relation": "calls",
      "confidence": "EXTRACTED",
      "confidence_score": 1.0,
      "source_file": "adapter.go",
      "source_location": "adapter.go:440",
      "weight": 1.0,
      "source": "adapter_loadpolicyline",
      "target": "adapter_loadfilteredpolicy"
    },
    {
      "relation": "calls",
      "confidence": "EXTRACTED",
      "confidence_score": 1.0,
      "source_file": "adapter_test.go",
      "source_location": "adapter_test.go:107",
      "weight": 1.0,
      "source": "adapter_loadpolicy",
      "target": "adaptertest_initpolicy"
    },
    {
      "relation": "references",
      "confidence": "EXTRACTED",
      "confidence_score": 1.0,
      "source_file": "docs/superpowers/specs/2026-05-07-gorm-adapter-baseline-design.md",
      "source_location": "lines 27-30",
      "weight": 1.0,
      "source": "adapter_loadpolicy",
      "target": "2026_05_07_gorm_adapter_baseline_design_usage_scenario_1_persist_policy"
    },
    {
      "relation": "references",
      "confidence": "EXTRACTED",
      "confidence_score": 1.0,
      "source_file": "docs/superpowers/specs/2026-05-07-gorm-adapter-baseline-design.md",
      "source_location": "lines 147-149",
      "weight": 1.0,
      "source": "adapter_loadpolicy",
      "target": "2026_05_07_gorm_adapter_baseline_design_ac_001_persist_adapter"
    },
    {
      "relation": "calls",
      "confidence": "EXTRACTED",
      "confidence_score": 1.0,
      "source_file": "adapter.go",
      "source_location": "adapter.go:435",
      "weight": 1.0,
      "source": "adapter_loadfilteredpolicy",
      "target": "adapter_filterquery"
    },
    {
      "relation": "references",
      "confidence": "INFERRED",
      "confidence_score": 0.85,
      "source_file": "adapter_test.go",
      "source_location": "adapter_test.go:320",
      "weight": 1.0,
      "source": "adapter_loadfilteredpolicy",
      "target": "adaptertest_testfilteredpolicy"
    },
    {
      "relation": "references",
      "confidence": "EXTRACTED",
      "confidence_score": 1.0,
      "source_file": "docs/superpowers/specs/2026-05-07-gorm-adapter-baseline-design.md",
      "source_location": "lines 95-119",
      "weight": 1.0,
      "source": "adapter_loadfilteredpolicy",
      "target": "2026_05_07_gorm_adapter_baseline_design_usage_scenario_3_filtered_policy_loading"
    },
    {
      "relation": "references",
      "confidence": "EXTRACTED",
      "confidence_score": 1.0,
      "source_file": "docs/superpowers/specs/2026-05-07-gorm-adapter-baseline-design.md",
      "source_location": "lines 150-151",
      "weight": 1.0,
      "source": "adapter_loadfilteredpolicy",
      "target": "2026_05_07_gorm_adapter_baseline_design_ac_002_persist_filteredadapter"
    },
    {
      "relation": "rationale_for",
      "confidence": "EXTRACTED",
      "confidence_score": 1.0,
      "source_file": "docs/superpowers/specs/2026-05-07-gorm-adapter-baseline-design.md",
      "source_location": "lines 97-119",
      "weight": 1.0,
      "source": "adapter_loadfilteredpolicy",
      "target": "2026_05_07_gorm_adapter_baseline_design_filtered_save_safety_invariant"
    },
    {
      "relation": "references",
      "confidence": "EXTRACTED",
      "confidence_score": 1.0,
      "source_file": "docs/superpowers/specs/2026-05-07-gorm-adapter-baseline-design.md",
      "source_location": "lines 110-113",
      "weight": 1.0,
      "source": "adapter_isfiltered",
      "target": "2026_05_07_gorm_adapter_baseline_design_usage_scenario_3_filtered_policy_loading"
    },
    {
      "relation": "references",
      "confidence": "EXTRACTED",
      "confidence_score": 1.0,
      "source_file": "docs/superpowers/specs/2026-05-07-gorm-adapter-baseline-design.md",
      "source_location": "lines 150-151",
      "weight": 1.0,
      "source": "adapter_isfiltered",
      "target": "2026_05_07_gorm_adapter_baseline_design_ac_002_persist_filteredadapter"
    },
    {
      "relation": "rationale_for",
      "confidence": "INFERRED",
      "confidence_score": 0.85,
      "source_file": "docs/superpowers/specs/2026-05-07-gorm-adapter-baseline-design.md",
      "source_location": "lines 193-196",
      "weight": 1.0,
      "source": "adapter_filterquery",
      "target": "2026_05_07_gorm_adapter_baseline_design_filter_v7_asymmetry"
    },
    {
      "relation": "calls",
      "confidence": "EXTRACTED",
      "confidence_score": 1.0,
      "source_file": "adapter.go",
      "source_location": "adapter.go:529-541",
      "weight": 1.0,
      "source": "adapter_savepolicyline",
      "target": "adapter_savepolicy"
    },
    {
      "relation": "calls",
      "confidence": "EXTRACTED",
      "confidence_score": 1.0,
      "source_file": "adapter.go",
      "source_location": "adapter.go:561",
      "weight": 1.0,
      "source": "adapter_savepolicyline",
      "target": "adapter_addpolicy"
    },
    {
      "relation": "calls",
      "confidence": "EXTRACTED",
      "confidence_score": 1.0,
      "source_file": "adapter.go",
      "source_location": "adapter.go:568",
      "weight": 1.0,
      "source": "adapter_savepolicyline",
      "target": "adapter_removepolicy"
    },
    {
      "relation": "calls",
      "confidence": "EXTRACTED",
      "confidence_score": 1.0,
      "source_file": "adapter.go",
      "source_location": "adapter.go:577",
      "weight": 1.0,
      "source": "adapter_savepolicyline",
      "target": "adapter_addpolicies"
    },
    {
      "relation": "calls",
      "confidence": "EXTRACTED",
      "confidence_score": 1.0,
      "source_file": "adapter.go",
      "source_location": "adapter.go:587",
      "weight": 1.0,
      "source": "adapter_savepolicyline",
      "target": "adapter_removepolicies"
    },
    {
      "relation": "calls",
      "confidence": "EXTRACTED",
      "confidence_score": 1.0,
      "source_file": "adapter.go",
      "source_location": "adapter.go:731-732",
      "weight": 1.0,
      "source": "adapter_savepolicyline",
      "target": "adapter_updatepolicy"
    },
    {
      "relation": "calls",
      "confidence": "EXTRACTED",
      "confidence_score": 1.0,
      "source_file": "adapter.go",
      "source_location": "adapter.go:740-743",
      "weight": 1.0,
      "source": "adapter_savepolicyline",
      "target": "adapter_updatepolicies"
    },
    {
      "relation": "calls",
      "confidence": "EXTRACTED",
      "confidence_score": 1.0,
      "source_file": "adapter.go",
      "source_location": "adapter.go:788",
      "weight": 1.0,
      "source": "adapter_savepolicyline",
      "target": "adapter_updatefilteredpolicies"
    },
    {
      "relation": "references",
      "confidence": "EXTRACTED",
      "confidence_score": 1.0,
      "source_file": "x_fork.tree-20260506.md",
      "source_location": "line 68",
      "weight": 1.0,
      "source": "adapter_savepolicyline",
      "target": "x_fork_tree_20260506_project_tree_index"
    },
    {
      "relation": "calls",
      "confidence": "EXTRACTED",
      "confidence_score": 1.0,
      "source_file": "adapter_test.go",
      "source_location": "adapter_test.go:97",
      "weight": 1.0,
      "source": "adapter_savepolicy",
      "target": "adaptertest_initpolicy"
    },
    {
      "relation": "references",
      "confidence": "EXTRACTED",
      "confidence_score": 1.0,
      "source_file": "docs/superpowers/specs/2026-05-07-gorm-adapter-baseline-design.md",
      "source_location": "lines 27-30",
      "weight": 1.0,
      "source": "adapter_savepolicy",
      "target": "2026_05_07_gorm_adapter_baseline_design_usage_scenario_1_persist_policy"
    },
    {
      "relation": "references",
      "confidence": "EXTRACTED",
      "confidence_score": 1.0,
      "source_file": "docs/superpowers/specs/2026-05-07-gorm-adapter-baseline-design.md",
      "source_location": "lines 114-116",
      "weight": 1.0,
      "source": "adapter_savepolicy",
      "target": "2026_05_07_gorm_adapter_baseline_design_usage_scenario_3_filtered_policy_loading"
    },
    {
      "relation": "references",
      "confidence": "EXTRACTED",
      "confidence_score": 1.0,
      "source_file": "docs/superpowers/specs/2026-05-07-gorm-adapter-baseline-design.md",
      "source_location": "lines 147-149",
      "weight": 1.0,
      "source": "adapter_savepolicy",
      "target": "2026_05_07_gorm_adapter_baseline_design_ac_001_persist_adapter"
    },
    {
      "relation": "rationale_for",
      "confidence": "EXTRACTED",
      "confidence_score": 1.0,
      "source_file": "docs/superpowers/specs/2026-05-07-gorm-adapter-baseline-design.md",
      "source_location": "lines 97-119",
      "weight": 1.0,
      "source": "adapter_savepolicy",
      "target": "2026_05_07_gorm_adapter_baseline_design_filtered_save_safety_invariant"
    },
    {
      "relation": "references",
      "confidence": "INFERRED",
      "confidence_score": 0.7,
      "source_file": "adapter_test.go",
      "source_location": null,
      "weight": 1.0,
      "source": "adapter_addpolicy",
      "target": "adaptertest_testautosave"
    },
    {
      "relation": "references",
      "confidence": "EXTRACTED",
      "confidence_score": 1.0,
      "source_file": "docs/superpowers/specs/2026-05-07-gorm-adapter-baseline-design.md",
      "source_location": "lines 46-48",
      "weight": 1.0,
      "source": "adapter_addpolicy",
      "target": "2026_05_07_gorm_adapter_baseline_design_usage_scenario_1_persist_policy"
    },
    {
      "relation": "references",
      "confidence": "EXTRACTED",
      "confidence_score": 1.0,
      "source_file": "docs/superpowers/specs/2026-05-07-gorm-adapter-baseline-design.md",
      "source_location": "lines 147-149",
      "weight": 1.0,
      "source": "adapter_addpolicy",
      "target": "2026_05_07_gorm_adapter_baseline_design_ac_001_persist_adapter"
    },
    {
      "relation": "calls",
      "confidence": "EXTRACTED",
      "confidence_score": 1.0,
      "source_file": "adapter.go",
      "source_location": "adapter.go:569",
      "weight": 1.0,
      "source": "adapter_removepolicy",
      "target": "adapter_rawdelete"
    },
    {
      "relation": "references",
      "confidence": "INFERRED",
      "confidence_score": 0.7,
      "source_file": "adapter_test.go",
      "source_location": null,
      "weight": 1.0,
      "source": "adapter_removepolicy",
      "target": "adaptertest_testautosave"
    },
    {
      "relation": "references",
      "confidence": "EXTRACTED",
      "confidence_score": 1.0,
      "source_file": "docs/superpowers/specs/2026-05-07-gorm-adapter-baseline-design.md",
      "source_location": "lines 147-149",
      "weight": 1.0,
      "source": "adapter_removepolicy",
      "target": "2026_05_07_gorm_adapter_baseline_design_ac_001_persist_adapter"
    },
    {
      "relation": "references",
      "confidence": "EXTRACTED",
      "confidence_score": 1.0,
      "source_file": "docs/superpowers/specs/2026-05-07-gorm-adapter-baseline-design.md",
      "source_location": "lines 152-153",
      "weight": 1.0,
      "source": "adapter_addpolicies",
      "target": "2026_05_07_gorm_adapter_baseline_design_ac_003_persist_batchadapter"
    },
    {
      "relation": "calls",
      "confidence": "EXTRACTED",
      "confidence_score": 1.0,
      "source_file": "adapter.go",
      "source_location": "adapter.go:588",
      "weight": 1.0,
      "source": "adapter_removepolicies",
      "target": "adapter_rawdelete"
    },
    {
      "relation": "references",
      "confidence": "EXTRACTED",
      "confidence_score": 1.0,
      "source_file": "docs/superpowers/specs/2026-05-07-gorm-adapter-baseline-design.md",
      "source_location": "lines 152-153",
      "weight": 1.0,
      "source": "adapter_removepolicies",
      "target": "2026_05_07_gorm_adapter_baseline_design_ac_003_persist_batchadapter"
    },
    {
      "relation": "calls",
      "confidence": "EXTRACTED",
      "confidence_score": 1.0,
      "source_file": "adapter.go",
      "source_location": "adapter.go:606",
      "weight": 1.0,
      "source": "adapter_removefilteredpolicy",
      "target": "adapter_checkqueryfield"
    },
    {
      "relation": "calls",
      "confidence": "EXTRACTED",
      "confidence_score": 1.0,
      "source_file": "adapter.go",
      "source_location": "adapter.go:603-635",
      "weight": 1.0,
      "source": "adapter_removefilteredpolicy",
      "target": "adapter_rawdelete"
    },
    {
      "relation": "references",
      "confidence": "INFERRED",
      "confidence_score": 0.7,
      "source_file": "adapter_test.go",
      "source_location": null,
      "weight": 1.0,
      "source": "adapter_removefilteredpolicy",
      "target": "adaptertest_testautosave"
    },
    {
      "relation": "references",
      "confidence": "EXTRACTED",
      "confidence_score": 1.0,
      "source_file": "docs/superpowers/specs/2026-05-07-gorm-adapter-baseline-design.md",
      "source_location": "lines 147-149",
      "weight": 1.0,
      "source": "adapter_removefilteredpolicy",
      "target": "2026_05_07_gorm_adapter_baseline_design_ac_001_persist_adapter"
    },
    {
      "relation": "semantically_similar_to",
      "confidence": "INFERRED",
      "confidence_score": 0.9,
      "source_file": "adapter.go",
      "source_location": null,
      "weight": 1.0,
      "source": "adapter_rawdelete",
      "target": "adapter_appendwhere"
    },
    {
      "relation": "semantically_similar_to",
      "confidence": "INFERRED",
      "confidence_score": 0.9,
      "source_file": "adapter.go",
      "source_location": null,
      "weight": 1.0,
      "source": "adapter_appendwhere",
      "target": "adapter_casbinrule_querystring"
    },
    {
      "relation": "references",
      "confidence": "EXTRACTED",
      "confidence_score": 1.0,
      "source_file": "docs/superpowers/specs/2026-05-07-gorm-adapter-baseline-design.md",
      "source_location": "lines 154-155",
      "weight": 1.0,
      "source": "adapter_updatepolicy",
      "target": "2026_05_07_gorm_adapter_baseline_design_ac_004_persist_updatableadapter"
    },
    {
      "relation": "references",
      "confidence": "EXTRACTED",
      "confidence_score": 1.0,
      "source_file": "docs/superpowers/specs/2026-05-07-gorm-adapter-baseline-design.md",
      "source_location": "lines 154-155",
      "weight": 1.0,
      "source": "adapter_updatepolicies",
      "target": "2026_05_07_gorm_adapter_baseline_design_ac_004_persist_updatableadapter"
    },
    {
      "relation": "calls",
      "confidence": "EXTRACTED",
      "confidence_score": 1.0,
      "source_file": "adapter.go",
      "source_location": "adapter.go:794",
      "weight": 1.0,
      "source": "adapter_updatefilteredpolicies",
      "target": "adapter_casbinrule_querystring"
    },
    {
      "relation": "calls",
      "confidence": "EXTRACTED",
      "confidence_score": 1.0,
      "source_file": "adapter.go",
      "source_location": "adapter.go:812",
      "weight": 1.0,
      "source": "adapter_updatefilteredpolicies",
      "target": "adapter_casbinrule_tostringpolicy"
    },
    {
      "relation": "references",
      "confidence": "EXTRACTED",
      "confidence_score": 1.0,
      "source_file": "docs/superpowers/specs/2026-05-07-gorm-adapter-baseline-design.md",
      "source_location": "lines 154-155",
      "weight": 1.0,
      "source": "adapter_updatefilteredpolicies",
      "target": "2026_05_07_gorm_adapter_baseline_design_ac_004_persist_updatableadapter"
    },
    {
      "relation": "calls",
      "confidence": "EXTRACTED",
      "confidence_score": 1.0,
      "source_file": "adapter_test.go",
      "source_location": "adapter_test.go:135",
      "weight": 1.0,
      "source": "adaptertest_initpolicy",
      "target": "adaptertest_initadapter"
    },
    {
      "relation": "calls",
      "confidence": "EXTRACTED",
      "confidence_score": 1.0,
      "source_file": "adapter_test.go",
      "source_location": "adapter_test.go:116",
      "weight": 1.0,
      "source": "adaptertest_initpolicy",
      "target": "adaptertest_testsaveload"
    },
    {
      "relation": "calls",
      "confidence": "EXTRACTED",
      "confidence_score": 1.0,
      "source_file": "adapter_test.go",
      "source_location": "adapter_test.go:497",
      "weight": 1.0,
      "source": "adaptertest_initadapter",
      "target": "adaptertest_testadapters"
    },
    {
      "relation": "calls",
      "confidence": "EXTRACTED",
      "confidence_score": 1.0,
      "source_file": "adapter_test.go",
      "source_location": "adapter_test.go:499",
      "weight": 1.0,
      "source": "adaptertest_testsaveload",
      "target": "adaptertest_testadapters"
    },
    {
      "relation": "calls",
      "confidence": "EXTRACTED",
      "confidence_score": 1.0,
      "source_file": "adapter_test.go",
      "source_location": "adapter_test.go:498",
      "weight": 1.0,
      "source": "adaptertest_testautosave",
      "target": "adaptertest_testadapters"
    },
    {
      "relation": "calls",
      "confidence": "EXTRACTED",
      "confidence_score": 1.0,
      "source_file": "adapter_test.go",
      "source_location": "adapter_test.go:518",
      "weight": 1.0,
      "source": "adaptertest_testfilteredpolicy",
      "target": "adaptertest_testadapters"
    },
    {
      "relation": "semantically_similar_to",
      "confidence": "INFERRED",
      "confidence_score": 0.95,
      "source_file": "open_sqlite3.go",
      "source_location": null,
      "weight": 1.0,
      "source": "open_opens_map",
      "target": "open_sqlite3_opens_map"
    },
    {
      "relation": "references",
      "confidence": "EXTRACTED",
      "confidence_score": 1.0,
      "source_file": "docs/superpowers/specs/2026-05-07-gorm-adapter-baseline-design.md",
      "source_location": "lines 22-52",
      "weight": 1.0,
      "source": "2026_05_07_gorm_adapter_baseline_design_baseline_spec",
      "target": "2026_05_07_gorm_adapter_baseline_design_usage_scenario_1_persist_policy"
    },
    {
      "relation": "references",
      "confidence": "EXTRACTED",
      "confidence_score": 1.0,
      "source_file": "docs/superpowers/specs/2026-05-07-gorm-adapter-baseline-design.md",
      "source_location": "lines 55-87",
      "weight": 1.0,
      "source": "2026_05_07_gorm_adapter_baseline_design_baseline_spec",
      "target": "2026_05_07_gorm_adapter_baseline_design_usage_scenario_2_existing_gorm_db"
    },
    {
      "relation": "references",
      "confidence": "EXTRACTED",
      "confidence_score": 1.0,
      "source_file": "docs/superpowers/specs/2026-05-07-gorm-adapter-baseline-design.md",
      "source_location": "lines 90-120",
      "weight": 1.0,
      "source": "2026_05_07_gorm_adapter_baseline_design_baseline_spec",
      "target": "2026_05_07_gorm_adapter_baseline_design_usage_scenario_3_filtered_policy_loading"
    },
    {
      "relation": "rationale_for",
      "confidence": "EXTRACTED",
      "confidence_score": 1.0,
      "source_file": "docs/superpowers/specs/2026-05-07-gorm-adapter-baseline-design.md",
      "source_location": "lines 6-9, 257-262",
      "weight": 1.0,
      "source": "2026_05_07_gorm_adapter_baseline_design_baseline_spec",
      "target": "2026_05_07_gorm_adapter_baseline_design_baseline_target_bc66b93"
    },
    {
      "relation": "rationale_for",
      "confidence": "EXTRACTED",
      "confidence_score": 1.0,
      "source_file": "docs/superpowers/specs/2026-05-07-gorm-adapter-baseline-design.md",
      "source_location": "lines 169-173",
      "weight": 1.0,
      "source": "2026_05_07_gorm_adapter_baseline_design_ac_008_six_constructors",
      "target": "2026_05_07_gorm_adapter_baseline_design_principle_v_minimal_surface"
    },
    {
      "relation": "rationale_for",
      "confidence": "EXTRACTED",
      "confidence_score": 1.0,
      "source_file": "docs/superpowers/specs/2026-05-07-gorm-adapter-baseline-design.md",
      "source_location": "lines 180-182",
      "weight": 1.0,
      "source": "2026_05_07_gorm_adapter_baseline_design_ac_011_driver_isolation_in_open_files",
      "target": "2026_05_07_gorm_adapter_baseline_design_principle_ii_cross_db_parity"
    },
    {
      "relation": "semantically_similar_to",
      "confidence": "INFERRED",
      "confidence_score": 0.95,
      "source_file": "x_fork.tree-20260506.md",
      "source_location": "lines 49-52",
      "weight": 1.0,
      "source": "2026_05_07_gorm_adapter_baseline_design_constructor_convergence_pattern",
      "target": "x_fork_tree_20260506_constructor_convergence_open"
    },
    {
      "relation": "semantically_similar_to",
      "confidence": "INFERRED",
      "confidence_score": 0.95,
      "source_file": "x_fork.tree-20260506.md",
      "source_location": "line 31",
      "weight": 1.0,
      "source": "2026_05_07_gorm_adapter_baseline_design_drift_glebarez_vs_gorm_io_sqlite",
      "target": "x_fork_tree_20260506_open_sqlite3_glebarez_drift_note"
    },
    {
      "relation": "semantically_similar_to",
      "confidence": "INFERRED",
      "confidence_score": 0.85,
      "source_file": "x_fork.tree-20260506.md",
      "source_location": "lines 45-48",
      "weight": 1.0,
      "source": "2026_05_07_gorm_adapter_baseline_design_drift_sqlite3_buildtag_conditional",
      "target": "x_fork_tree_20260506_build_tag_mutex_open_files"
    }
  ],
  "hyperedges": [
    {
      "id": "hg_persist_interface_contracts",
      "label": "Casbin persist interface contracts the Adapter implements",
      "nodes": [
        "2026_05_07_gorm_adapter_baseline_design_ac_001_persist_adapter",
        "2026_05_07_gorm_adapter_baseline_design_ac_002_persist_filteredadapter",
        "2026_05_07_gorm_adapter_baseline_design_ac_003_persist_batchadapter",
        "2026_05_07_gorm_adapter_baseline_design_ac_004_persist_updatableadapter",
        "adapter_adapter"
      ],
      "relation": "implement",
      "confidence": "EXTRACTED",
      "confidence_score": 1.0,
      "source_file": "docs/superpowers/specs/2026-05-07-gorm-adapter-baseline-design.md"
    },
    {
      "id": "hg_six_constructors_minimal_surface",
      "label": "Six top-level constructors governed by Minimal Surface principle",
      "nodes": [
        "adapter_newadapter",
        "adapter_newadapterbydb",
        "adapter_newadapterbydbusetablename",
        "adapter_newadapterbydbwithcustomtable",
        "adapter_newfilteredadapter",
        "adapter_newadapterbymuldb",
        "2026_05_07_gorm_adapter_baseline_design_ac_008_six_constructors"
      ],
      "relation": "participate_in",
      "confidence": "EXTRACTED",
      "confidence_score": 1.0,
      "source_file": "docs/superpowers/specs/2026-05-07-gorm-adapter-baseline-design.md"
    },
    {
      "id": "hg_three_priority_usage_scenarios",
      "label": "Three Usage Scenarios (P1/P2/P3) framing baseline behaviour",
      "nodes": [
        "2026_05_07_gorm_adapter_baseline_design_usage_scenario_1_persist_policy",
        "2026_05_07_gorm_adapter_baseline_design_usage_scenario_2_existing_gorm_db",
        "2026_05_07_gorm_adapter_baseline_design_usage_scenario_3_filtered_policy_loading",
        "2026_05_07_gorm_adapter_baseline_design_baseline_spec"
      ],
      "relation": "form",
      "confidence": "EXTRACTED",
      "confidence_score": 1.0,
      "source_file": "docs/superpowers/specs/2026-05-07-gorm-adapter-baseline-design.md"
    }
  ],
  "built_at_commit": "c0067516417bc190c579b89bc6a6a18e54158a36"
}